image_token/__init__.py
image_token/main.py
image_token/base/__init__.py
image_token/base/base.py
image_token/frameworks/__init__.py
image_token/frameworks/langchain_callback.py
image_token/models/__init__.py
image_token/models/gemini_helper.py
image_token/models/openai_helper.py
image_token/utils/__init__.py
image_token/utils/caching_utils.py
image_token/utils/config.py
image_token/utils/utils.py
image_token/utils/validate.py
image_token-0.1.6.dist-info/licenses/LICENSE
image_token-0.1.6.dist-info/METADATA
image_token-0.1.6.dist-info/WHEEL
image_token-0.1.6.dist-info/top_level.txt
image_token-0.1.6.dist-info/RECORD
