Metadata-Version: 2.4
Name: image-token
Version: 0.1.6
Summary: A package to calculate the number of tokens in an image or folder
License:                                  Apache License
Project-URL: Homepage, https://github.com/srinathmkce/imagetoken
Requires-Python: >=3.9
License-File: LICENSE
Requires-Dist: pytest>=8.3.5
Requires-Dist: pillow<12.0.0,>=11.2.1
Requires-Dist: langchain-openai<0.4.0,>=0.3.18
Requires-Dist: python-dotenv<2.0.0,>=1.1.0
Requires-Dist: ruff<0.12.0,>=0.11.11
Requires-Dist: requests<3.0.0,>=2.32.4
Requires-Dist: google-genai<2.0.0,>=1.0.0
Dynamic: license-file
